project_mem_mcp/__init__.py
project_mem_mcp/server.py
project_mem_mcp-0.1.2.dist-info/licenses/LICENSE
project_mem_mcp-0.1.2.dist-info/METADATA
project_mem_mcp-0.1.2.dist-info/WHEEL
project_mem_mcp-0.1.2.dist-info/entry_points.txt
project_mem_mcp-0.1.2.dist-info/top_level.txt
project_mem_mcp-0.1.2.dist-info/RECORD
