Metadata-Version: 2.4
Name: project-mem-mcp
Version: 0.1.2
Summary: An MCP Server to store and retreive project information from memory file
Author: PYNESYS LLC
License: MIT
Requires-Python: >=3.11
License-File: LICENSE
Requires-Dist: fastmcp<3.0.0,>=2.2.0
Dynamic: license-file
